lttngmouse/__init__.py
lttngmouse/cli.py
lttngmouse/impl.py
lttngmouse/pub.py
lttngmouse-0.1.0.dist-info/LICENSE
lttngmouse-0.1.0.dist-info/METADATA
lttngmouse-0.1.0.dist-info/WHEEL
lttngmouse-0.1.0.dist-info/entry_points.txt
lttngmouse-0.1.0.dist-info/RECORD
