Metadata-Version: 2.3
Name: lttngmouse
Version: 0.1.0
Summary: LTTng distribution package dynamic data
License: MIT
Keywords: lttng,distribution,package
Author: Philippe Proulx
Author-email: eeppeliteloop@gmail.com
Requires-Python: >=3.9,<4.0
Classifier: License :: OSI Approved :: MIT License
Classifier: Programming Language :: Python :: 3
Classifier: Programming Language :: Python :: 3.9
Classifier: Programming Language :: Python :: 3.10
Classifier: Programming Language :: Python :: 3.11
Classifier: Programming Language :: Python :: 3.12
Classifier: Programming Language :: Python :: 3.13
Requires-Dist: aiohttp (>=3.11,<4.0)
Requires-Dist: beautifulsoup4 (>=4.13,<5.0)
Requires-Dist: packaging (>=24.0,<25.0)
Requires-Dist: terminaltables3 (>=4.0,<5.0)
Project-URL: Repository, https://github.com/lttng/lttngmouse/
